setup.py
objdem/__init__.py
objdem/objdem.py
objdem.egg-info/PKG-INFO
objdem.egg-info/SOURCES.txt
objdem.egg-info/dependency_links.txt
objdem.egg-info/requires.txt
objdem.egg-info/top_level.txt