Metadata-Version: 1.0
Name: objdem
Version: 1.0.12
Summary: Generates an .obj file representing a digital elevation map from coordinate input
Home-page: https://github.com/kevinforrestconnors/objdem
Author: Kevin Forrest Connors
Author-email: kevinforrestconnors@gmail.com
License: MIT
Platform: UNKNOWN
